{
  "_id": "TASK-14.7",
  "taskId": "TASK-14.7",
  "moduleId": "14",
  "moduleName": "Mobile",
  "title": "Rich notifications with actions",
  "description": "Implements: Rich notifications with actions.",
  "storyPoints": 8,
  "estimatedHours": null,
  "priority": "Medium",
  "status": "completed",
  "assignedTo": "",
  "sprintId": "SPRINT-014",
  "sprintNumber": 14,
  "dependencies": [],
  "tags": ["mobile"],
  "tech": "",
  "acceptanceCriteria": "",
  "createdAt": "2025-10-11T00:00:00",
  "updatedAt": "2025-10-11T00:00:00",
  "lastUpdated": "2025-10-13T02:27:58.427Z",
  "completedAt": "2025-10-14T02:45:40.791Z",
  "executionDetails": {
    "completedAt": "2025-10-14T02:45:40.791Z",
    "executionAttempts": 1
  },
  "executionStatus": "executed"
}
